pdfbox/__init__.py
pdfbox/pdfbox-app-2.0.28.jar
python_pdfbox_v2-2.0.28.4.dist-info/AUTHORS.rst
python_pdfbox_v2-2.0.28.4.dist-info/LICENSE.rst
python_pdfbox_v2-2.0.28.4.dist-info/METADATA
python_pdfbox_v2-2.0.28.4.dist-info/WHEEL
python_pdfbox_v2-2.0.28.4.dist-info/top_level.txt
python_pdfbox_v2-2.0.28.4.dist-info/RECORD
