Metadata-Version: 2.1
Name: python-pdfbox-v2
Version: 2.0.28.4
Summary: Python interface to Apache PDFBox command-line tools.
Home-page: https://github.com/py-hacks/python-pdfbox
Author: Fakabbir Amin
Author-email: f4amin@gmail.com
License: Apache
Classifier: Development Status :: 3 - Alpha
Classifier: Environment :: Console
Classifier: Intended Audience :: Developers
Classifier: License :: OSI Approved :: Apache Software License
Classifier: Operating System :: OS Independent
Classifier: Programming Language :: Python :: 3
Classifier: Topic :: Software Development
Requires-Python: >=3
License-File: LICENSE.rst
License-File: AUTHORS.rst
Requires-Dist: jpype1
Requires-Dist: setuptools
